MANIFEST.in
README.md
setup.py
pyscript/__init__.py
pyscript/__init__.pyi
pyscript/__main__.py
pyscript/this.py
pyscript/core/__init__.py
pyscript/core/analyzer.py
pyscript/core/bases.py
pyscript/core/buffer.py
pyscript/core/cache.py
pyscript/core/checks.py
pyscript/core/constants.py
pyscript/core/context.py
pyscript/core/exceptions.py
pyscript/core/handlers.py
pyscript/core/highlight.py
pyscript/core/interpreter.py
pyscript/core/lexer.py
pyscript/core/mapping.py
pyscript/core/nodes.py
pyscript/core/objects.py
pyscript/core/parser.py
pyscript/core/position.py
pyscript/core/pysbuiltins.py
pyscript/core/results.py
pyscript/core/runner.py
pyscript/core/shell.py
pyscript/core/symtab.py
pyscript/core/token.py
pyscript/core/version.py
pyscript/core/other/copyright
pyscript/core/other/credits
pyscript/core/other/license
pyscript/core/utils/__init__.py
pyscript/core/utils/ansi.py
pyscript/core/utils/debug.py
pyscript/core/utils/decorators.py
pyscript/core/utils/generic.py
pyscript/core/utils/jsdict.py
pyscript/core/utils/module.py
pyscript/core/utils/path.py
pyscript/core/utils/similarity.py
pyscript/core/utils/string.py
pyscript/lib/__hello__.pys
pyscript/lib/ansi.pys
pyscript/lib/brainfuck.pys
pyscript/lib/dis.pys
pyscript/lib/explorer.pys
pyscript/lib/getch.pys
pyscript/lib/inspect.pys
pyscript/lib/jsdict.pys
pyscript/lib/keyword.pys
pyscript/lib/opcode.pys
pyscript/lib/parser.pys
pyscript/lib/site.pys
pyscript/lib/symtable.pys
pyscript/lib/sys.pys
pyscript/lib/token.pys
pyscript/lib/ast/__init__.pys
pyscript/lib/ast/ast_dump.py
pyscript/lib/ast/ast_literal_eval.py
pyscript/lib/ast/ast_unparse.py
pyscript/lib/ast/ast_walk.py
pyscript/lib/fpstimer/__init__.pys
pyscript/lib/fpstimer/py_fpstimer.py
pyscript/lib/tokenize/__init__.pys
pyscript/lib/tokenize/tok_untokenize.py
pyscript/site-packages/this.pys
pyscript_programming_language.egg-info/PKG-INFO
pyscript_programming_language.egg-info/SOURCES.txt
pyscript_programming_language.egg-info/dependency_links.txt
pyscript_programming_language.egg-info/requires.txt
pyscript_programming_language.egg-info/top_level.txt