Metadata-Version: 2.4
Name: pyscript-programming-language
Version: 1.11.0
Summary: PyScript Programming Language
Home-page: https://azzammuhyala.github.io/pyscript
Author: azzammuhyala
Author-email: azzammuhyala@gmail.com
License: MIT
Project-URL: Source, https://github.com/azzammuhyala/pyscript
Project-URL: Bug Tracker, https://github.com/azzammuhyala/pyscript/issues
Keywords: pyscript,pyslang,pys,programming,language,programming language
Classifier: Programming Language :: Python
Classifier: Programming Language :: Python :: 3
Classifier: Intended Audience :: Developers
Classifier: Topic :: Software Development :: Libraries :: Python Modules
Classifier: Topic :: Software Development :: Interpreters
Classifier: Topic :: Software Development :: Compilers
Requires-Python: >=3.10
Provides-Extra: other
Requires-Dist: beartype; extra == "other"
Requires-Dist: pygments; extra == "other"
Dynamic: author
Dynamic: author-email
Dynamic: classifier
Dynamic: description
Dynamic: description-content-type
Dynamic: home-page
Dynamic: keywords
Dynamic: license
Dynamic: project-url
Dynamic: provides-extra
Dynamic: requires-python
Dynamic: summary
